CHANGELOG.md
LICENSE.txt
MANIFEST.in
README.md
setup.cfg
setup.py
lib/dcso/glosom/__init__.py
lib/dcso/glosom/constants.py
lib/dcso/glosom/glosom.py
lib/dcso/glosom/test_glosom.py
lib/dcso/portal/__init__.py
lib/dcso/portal/_version.py
lib/dcso/portal/abstracts.py
lib/dcso/portal/api.py
lib/dcso/portal/exceptions.py
lib/dcso/portal/test_api.py
lib/dcso/portal/auth/__init__.py
lib/dcso/portal/auth/auth.py
lib/dcso/portal/auth/rbac.py
lib/dcso/portal/auth/test_auth.py
lib/dcso/portal/auth/test_token.py
lib/dcso/portal/auth/token.py
lib/dcso/portal/util/__init__.py
lib/dcso/portal/util/graphql.py
lib/dcso/portal/util/networking.py
lib/dcso/portal/util/temporal.py
lib/dcso/portal/util/test_graphql.py
lib/dcso/portal/util/test_temporal.py
lib/dcso/portal/util/test_utils.py
lib/dcso_portal_python_sdk.egg-info/PKG-INFO
lib/dcso_portal_python_sdk.egg-info/SOURCES.txt
lib/dcso_portal_python_sdk.egg-info/dependency_links.txt
lib/dcso_portal_python_sdk.egg-info/top_level.txt