Metadata-Version: 2.1
Name: dcso-portal-python-sdk
Version: 1.0.0b4
Summary: DCSO Portal SDK
Home-page: https://dcso.github.io/dcso-portal-python-sdk/dcso/portal/
Author: DCSO GmbH
Author-email: portal-support@dcso.de
License: MIT License
Platform: Any
Classifier: Programming Language :: Python :: 3 :: Only
Classifier: Programming Language :: Python :: 3.7
Classifier: Operating System :: OS Independent
Classifier: Development Status :: 4 - Beta
Classifier: License :: OSI Approved :: MIT License
Classifier: Topic :: Software Development
Classifier: Topic :: Software Development :: Version Control :: Git
